MANIFEST.in
README.md
setup.py
typo_pypi/__init__.py
typo_pypi/algos.py
typo_pypi/analizer.py
typo_pypi/blacklist.json
typo_pypi/main.py
typo_pypi/package.py
typo_pypi/results.json
typo_pypi/results1.json
typo_pypi/server.py
typo_pypi/top-pypi-packages-30-days.json
typo_pypi/typo_packages.txt
typo_pypi/validater.py
typo_pypi.egg-info/PKG-INFO
typo_pypi.egg-info/SOURCES.txt
typo_pypi.egg-info/dependency_links.txt
typo_pypi.egg-info/requires.txt
typo_pypi.egg-info/top_level.txt
typo_pypi/yara/crypto.yara
typo_pypi/yara/fragus.yara
typo_pypi/yara/pypi.yara
typo_pypi/yara/setup.yara