Metadata-Version: 2.1
Name: typo-pypi
Version: 0.1.4
Summary: experimental approach for an empirical study for my thesis
Home-page: https://github.com/leodelasoul/typo_pypi
Author: Leonid Ricker
Author-email: l.ricker93@web.de
License: MIT
Platform: UNKNOWN
Classifier: License :: OSI Approved :: MIT License
Classifier: Programming Language :: Python
Classifier: Programming Language :: Python :: 3
Classifier: Programming Language :: Python :: 3.6
Classifier: Programming Language :: Python :: Implementation :: CPython
Classifier: Programming Language :: Python :: Implementation :: PyPy
Requires-Python: >=3.6.0
